{
  "meta": {
    "fs": 200,
    "win_sec": 4.0,
    "overlap": 0.5,
    "bandpass": [
      0.5,
      45.0
    ],
    "notch": 60.0,
    "montage_id": 0,
    "split_ratios": [
      0.6,
      0.2,
      0.2
    ],
    "canon_ch": [
      "Fp1",
      "Fp2",
      "C3",
      "C4",
      "P3",
      "P4",
      "O1",
      "O2"
    ]
  },
  "totals": {
    "train": 106583,
    "val": 36782,
    "test": 36202
  },
  "artifact_counts": {
    "train": {
      "none": 54927,
      "eye": 16504,
      "electrode": 12497,
      "muscle": 20646,
      "chewing": 1962,
      "shiver": 47
    },
    "val": {
      "eye": 5792,
      "none": 17254,
      "muscle": 9122,
      "electrode": 4614
    },
    "test": {
      "none": 17615,
      "eye": 2914,
      "electrode": 6663,
      "muscle": 8494,
      "chewing": 412,
      "shiver": 104
    }
  },
  "agebin_counts": {
    "train": {
      "2": 106583
    },
    "val": {
      "2": 36782
    },
    "test": {
      "2": 36202
    }
  },
  "montage_counts": {
    "train": {
      "0": 106583
    },
    "val": {
      "0": 36782
    },
    "test": {
      "0": 36202
    }
  },
  "seizure_counts": {
    "train": 11714,
    "val": 1340,
    "test": 8673
  },
  "intensity_hist_10bins": {
    "train": [
      54913,
      0,
      0,
      0,
      0,
      0,
      0,
      0,
      0,
      51670
    ],
    "val": [
      17254,
      0,
      0,
      0,
      0,
      0,
      0,
      0,
      0,
      19528
    ],
    "test": [
      17615,
      0,
      0,
      0,
      0,
      0,
      0,
      0,
      0,
      18587
    ]
  },
  "intensity_stats": {
    "train": {
      "mean": 0.4847862422466278,
      "std": 0.4997682571411133
    },
    "val": {
      "mean": 0.5309116244316101,
      "std": 0.49904337525367737
    },
    "test": {
      "mean": 0.5134245753288269,
      "std": 0.4998196065425873
    }
  },
  "psd": {
    "freqs": [
      0.0,
      0.390625,
      0.78125,
      1.171875,
      1.5625,
      1.953125,
      2.34375,
      2.734375,
      3.125,
      3.515625,
      3.90625,
      4.296875,
      4.6875,
      5.078125,
      5.46875,
      5.859375,
      6.25,
      6.640625,
      7.03125,
      7.421875,
      7.8125,
      8.203125,
      8.59375,
      8.984375,
      9.375,
      9.765625,
      10.15625,
      10.546875,
      10.9375,
      11.328125,
      11.71875,
      12.109375,
      12.5,
      12.890625,
      13.28125,
      13.671875,
      14.0625,
      14.453125,
      14.84375,
      15.234375,
      15.625,
      16.015625,
      16.40625,
      16.796875,
      17.1875,
      17.578125,
      17.96875,
      18.359375,
      18.75,
      19.140625,
      19.53125,
      19.921875,
      20.3125,
      20.703125,
      21.09375,
      21.484375,
      21.875,
      22.265625,
      22.65625,
      23.046875,
      23.4375,
      23.828125,
      24.21875,
      24.609375,
      25.0,
      25.390625,
      25.78125,
      26.171875,
      26.5625,
      26.953125,
      27.34375,
      27.734375,
      28.125,
      28.515625,
      28.90625,
      29.296875,
      29.6875,
      30.078125,
      30.46875,
      30.859375,
      31.25,
      31.640625,
      32.03125,
      32.421875,
      32.8125,
      33.203125,
      33.59375,
      33.984375,
      34.375,
      34.765625,
      35.15625,
      35.546875,
      35.9375,
      36.328125,
      36.71875,
      37.109375,
      37.5,
      37.890625,
      38.28125,
      38.671875,
      39.0625,
      39.453125,
      39.84375,
      40.234375,
      40.625,
      41.015625,
      41.40625,
      41.796875,
      42.1875,
      42.578125,
      42.96875,
      43.359375,
      43.75,
      44.140625,
      44.53125,
      44.921875,
      45.3125,
      45.703125,
      46.09375,
      46.484375,
      46.875,
      47.265625,
      47.65625,
      48.046875,
      48.4375,
      48.828125,
      49.21875,
      49.609375,
      50.0,
      50.390625,
      50.78125,
      51.171875,
      51.5625,
      51.953125,
      52.34375,
      52.734375,
      53.125,
      53.515625,
      53.90625,
      54.296875,
      54.6875,
      55.078125,
      55.46875,
      55.859375,
      56.25,
      56.640625,
      57.03125,
      57.421875,
      57.8125,
      58.203125,
      58.59375,
      58.984375,
      59.375,
      59.765625,
      60.15625,
      60.546875,
      60.9375,
      61.328125,
      61.71875,
      62.109375,
      62.5,
      62.890625,
      63.28125,
      63.671875,
      64.0625,
      64.453125,
      64.84375,
      65.234375,
      65.625,
      66.015625,
      66.40625,
      66.796875,
      67.1875,
      67.578125,
      67.96875,
      68.359375,
      68.75,
      69.140625,
      69.53125,
      69.921875,
      70.3125,
      70.703125,
      71.09375,
      71.484375,
      71.875,
      72.265625,
      72.65625,
      73.046875,
      73.4375,
      73.828125,
      74.21875,
      74.609375,
      75.0,
      75.390625,
      75.78125,
      76.171875,
      76.5625,
      76.953125,
      77.34375,
      77.734375,
      78.125,
      78.515625,
      78.90625,
      79.296875,
      79.6875,
      80.078125,
      80.46875,
      80.859375,
      81.25,
      81.640625,
      82.03125,
      82.421875,
      82.8125,
      83.203125,
      83.59375,
      83.984375,
      84.375,
      84.765625,
      85.15625,
      85.546875,
      85.9375,
      86.328125,
      86.71875,
      87.109375,
      87.5,
      87.890625,
      88.28125,
      88.671875,
      89.0625,
      89.453125,
      89.84375,
      90.234375,
      90.625,
      91.015625,
      91.40625,
      91.796875,
      92.1875,
      92.578125,
      92.96875,
      93.359375,
      93.75,
      94.140625,
      94.53125,
      94.921875,
      95.3125,
      95.703125,
      96.09375,
      96.484375,
      96.875,
      97.265625,
      97.65625,
      98.046875,
      98.4375,
      98.828125,
      99.21875,
      99.609375,
      100.0
    ],
    "overall": [
      0.018239488825201988,
      0.10425343364477158,
      0.16542842984199524,
      0.10943321138620377,
      0.06985480338335037,
      0.04635520651936531,
      0.03540249168872833,
      0.02780565805733204,
      0.0229808259755373,
      0.01864510588347912,
      0.015637507662177086,
      0.014116287231445312,
      0.012699499726295471,
      0.011886680498719215,
      0.010736055672168732,
      0.010163363069295883,
      0.009776445105671883,
      0.009499571286141872,
      0.009870026260614395,
      0.010355024598538876,
      0.011313664726912975,
      0.011822398751974106,
      0.011862557381391525,
      0.011305495165288448,
      0.01008992176502943,
      0.00975286215543747,
      0.009543050080537796,
      0.008497875183820724,
      0.007357945665717125,
      0.006454715970903635,
      0.005916820373386145,
      0.005404394119977951,
      0.004984342958778143,
      0.004734294023364782,
      0.004520772024989128,
      0.004406744614243507,
      0.004279651213437319,
      0.0041686431504786015,
      0.004032024648040533,
      0.0038761405739933252,
      0.003751675132662058,
      0.003592337481677532,
      0.003469800343737006,
      0.003343116259202361,
      0.0031944941729307175,
      0.003138359636068344,
      0.0031221157405525446,
      0.0030758872162550688,
      0.0029584108851850033,
      0.002910388633608818,
      0.0028489166870713234,
      0.002806727308779955,
      0.0027997775468975306,
      0.002718288917094469,
      0.002646828768774867,
      0.002528113080188632,
      0.002458632690832019,
      0.002419941360130906,
      0.0023002002853900194,
      0.0022525128442794085,
      0.002187240868806839,
      0.002129188971593976,
      0.002073622075840831,
      0.002026593079790473,
      0.0020121841225773096,
      0.0019422386540099978,
      0.0019045242806896567,
      0.0018704724498093128,
      0.0018112336983904243,
      0.0017678278964012861,
      0.0017330514965578914,
      0.001743876957334578,
      0.0017006212146952748,
      0.0016536579933017492,
      0.0016024047508835793,
      0.0015699065988883376,
      0.0015597440069541335,
      0.0015311932656913996,
      0.0015007532201707363,
      0.0014895383501425385,
      0.0014636090490967035,
      0.0014388666022568941,
      0.0014166630571708083,
      0.0013815915444865823,
      0.001364656025543809,
      0.0013617444783449173,
      0.0013287278125062585,
      0.001285475678741932,
      0.00126108736731112,
      0.001224030158482492,
      0.0012045892653986812,
      0.0011890724999830127,
      0.0011705358047038317,
      0.001144341193139553,
      0.0011101305717602372,
      0.0010757803684100509,
      0.0010544909164309502,
      0.0010048948461189866,
      0.0009637440089136362,
      0.0009160669287666678,
      0.0008899499662220478,
      0.0008591819787397981,
      0.0008122086292132735,
      0.0007619104580953717,
      0.0007202706183306873,
      0.0006963419145904481,
      0.0006631470168940723,
      0.0006233685417100787,
      0.0005739775369875133,
      0.0005325765814632177,
      0.0004929408896714449,
      0.0004557768988888711,
      0.0004998148651793599,
      0.0004477409820538014,
      0.0003492521063890308,
      0.00030932703521102667,
      0.0002730146807152778,
      0.0002432871115161106,
      0.00021889751951675862,
      0.0001936728658620268,
      0.00017127383034676313,
      0.00015220785280689597,
      0.00013207861047703773,
      0.00011560446728253737,
      0.00010199050302617252,
      8.701468323124573e-05,
      7.435846055159345e-05,
      6.247975397855043e-05,
      5.3837542509427294e-05,
      4.6015022235224023e-05,
      3.81438439944759e-05,
      3.266488783992827e-05,
      2.7703730665962212e-05,
      2.3069767848937772e-05,
      1.9392618924030103e-05,
      1.629696816962678e-05,
      1.3596533790405374e-05,
      1.1477644875412807e-05,
      9.42928727454273e-06,
      7.810338502167724e-06,
      6.477789156633662e-06,
      5.206369678489864e-06,
      4.285705927031813e-06,
      3.4945439892908325e-06,
      2.8302217742748326e-06,
      2.2332965272653382e-06,
      1.7550364646012895e-06,
      1.3677210972673493e-06,
      1.0177861895499518e-06,
      7.145251288420695e-07,
      4.531828494691581e-07,
      2.3157403461482318e-07,
      7.69410775092183e-08,
      1.2005746619081492e-08,
      4.993449209678147e-09,
      2.74610307826606e-08,
      6.651993089690222e-08,
      9.59059107685789e-08,
      1.0522795435008447e-07,
      1.027561751243411e-07,
      9.457087912778661e-08,
      8.005209650718825e-08,
      6.681573694322651e-08,
      5.516458756460452e-08,
      4.580155277267295e-08,
      3.8025643078754e-08,
      3.077810006857362e-08,
      2.4575159685014114e-08,
      1.953407391397377e-08,
      1.5302168421271745e-08,
      1.2157167716964068e-08,
      9.609792961384755e-09,
      7.643739863283372e-09,
      6.0269309543059535e-09,
      4.730099867344961e-09,
      3.859276009876567e-09,
      3.0417095508994407e-09,
      2.3910406987681654e-09,
      1.88440596460282e-09,
      1.4951326843259949e-09,
      1.1611362982222317e-09,
      9.003603418378248e-10,
      6.869395052788718e-10,
      5.356191601357807e-10,
      4.2257958243752114e-10,
      3.2492522561433645e-10,
      2.4998172976076205e-10,
      1.887386219534548e-10,
      1.4346697441158796e-10,
      1.1146230466385632e-10,
      8.596488104695155e-11,
      6.460686152731654e-11,
      4.8749060344022155e-11,
      3.687519387063354e-11,
      3.7057145546581793e-11,
      3.504288526023913e-11,
      1.6786457640582952e-11,
      1.14264630743377e-11,
      8.24085244488515e-12,
      6.010766537278833e-12,
      4.411156769718039e-12,
      3.213843037183639e-12,
      2.3732584907704135e-12,
      1.7277238667512407e-12,
      1.2454705235892538e-12,
      8.883286901212317e-13,
      6.253094830127592e-13,
      4.362329724880154e-13,
      3.040364997524553e-13,
      2.1541317720471381e-13,
      1.4811123247998603e-13,
      1.0236010308676061e-13,
      7.081972676478351e-14,
      4.913849546445831e-14,
      3.274923125111233e-14,
      2.208409202850061e-14,
      1.506028307163114e-14,
      1.0206261664535542e-14,
      6.860962214078623e-15,
      4.734505905270962e-15,
      3.26613193955827e-15,
      2.3643789698454473e-15,
      1.7308560294187624e-15,
      1.3310783952922428e-15,
      1.0639415679036552e-15,
      8.911232356203732e-16,
      7.77857936973969e-16,
      6.976586340664453e-16,
      6.424967251072522e-16,
      6.000509512082736e-16,
      5.63627581564273e-16,
      5.358476537514105e-16,
      5.105946369784444e-16,
      4.894762527188226e-16,
      4.669864691780369e-16,
      4.505541888199811e-16,
      4.3220793163848575e-16,
      4.1577880118420253e-16,
      4.0127349431137065e-16,
      3.868309208161948e-16,
      3.7419048932564125e-16,
      3.6274834475765654e-16,
      3.480110302666158e-16,
      3.4203031591451038e-16,
      3.289850820845081e-16,
      3.2322374926574155e-16,
      3.1299352355682053e-16,
      3.073808714900767e-16,
      3.018131915788762e-16,
      2.94041796636716e-16,
      2.9108477814807163e-16,
      2.86719964431311e-16,
      2.836061389683062e-16,
      2.804718788354489e-16,
      2.7969117915587643e-16,
      2.780166479587139e-16,
      1.3890180958623971e-16
    ],
    "none": [
      0.0113466065376997,
      0.058620695024728775,
      0.0968061164021492,
      0.06983290612697601,
      0.04559895023703575,
      0.03326186165213585,
      0.026926293969154358,
      0.023561565205454826,
      0.019257763400673866,
      0.015460987575352192,
      0.01331785786896944,
      0.012138226069509983,
      0.011211966164410114,
      0.010423261672258377,
      0.009646309539675713,
      0.009304618462920189,
      0.008994362317025661,
      0.009157344698905945,
      0.009825662709772587,
      0.010880393907427788,
      0.01196838915348053,
      0.012456453405320644,
      0.012723653577268124,
      0.01220468059182167,
      0.01068684458732605,
      0.010390073992311954,
      0.010377705097198486,
      0.008813189342617989,
      0.007314664777368307,
      0.00629285117611289,
      0.005623863078653812,
      0.005003100726753473,
      0.004528851248323917,
      0.004260259680449963,
      0.00403680931776762,
      0.003887241007760167,
      0.003727458417415619,
      0.003540606703609228,
      0.0033607669174671173,
      0.0032057592179626226,
      0.0030209673568606377,
      0.0028327826876193285,
      0.0027337991632521152,
      0.0026339164469391108,
      0.0025041340850293636,
      0.0024090625811368227,
      0.002372522372752428,
      0.0023155738599598408,
      0.002225199481472373,
      0.002157642738893628,
      0.0021025172900408506,
      0.002072189236059785,
      0.002030022442340851,
      0.0019267027964815497,
      0.0018620361806824803,
      0.0017739827744662762,
      0.001720412983559072,
      0.0016477040480822325,
      0.001565895276144147,
      0.0015297909267246723,
      0.0014808315318077803,
      0.0014171444345265627,
      0.001340074697509408,
      0.001296433387324214,
      0.0012580878101289272,
      0.0011834321776404977,
      0.001130161341279745,
      0.0010948323179036379,
      0.001055361470207572,
      0.0010146719869226217,
      0.0009714309708215296,
      0.0009382458520121872,
      0.0009053343674167991,
      0.000858008221257478,
      0.0008015332277864218,
      0.0007746421615593135,
      0.000764561234973371,
      0.0007319102296605706,
      0.000678610522300005,
      0.0006425842293538153,
      0.0006182139040902257,
      0.0005969044286757708,
      0.0005727039533667266,
      0.0005461802938953042,
      0.0005213996046222746,
      0.0005020466051064432,
      0.0004830931720789522,
      0.00046555118751712143,
      0.00044455763418227434,
      0.0004332133976276964,
      0.0004264759481884539,
      0.0004010226984973997,
      0.00038603332359343767,
      0.00037915940629318357,
      0.0003669553843792528,
      0.00035289095831103623,
      0.0003413640952203423,
      0.0003261120873503387,
      0.0003091421094723046,
      0.0002912971831392497,
      0.0002875410136766732,
      0.0002763860102277249,
      0.00026295502902939916,
      0.0002509433834347874,
      0.0002337039913982153,
      0.00022030051331967115,
      0.00020540952391456813,
      0.00019661503029055893,
      0.00018476117111276835,
      0.00016612131730653346,
      0.00015287022688426077,
      0.00013834038691129535,
      0.00012659675849135965,
      0.0001143687914009206,
      0.00010442075290484354,
      9.493401012150571e-05,
      8.355124737136066e-05,
      7.384727359749377e-05,
      6.520001625176519e-05,
      5.6400211178697646e-05,
      4.9598587793298066e-05,
      4.395384166855365e-05,
      3.8404865335905924e-05,
      3.328735692775808e-05,
      2.8863902116427198e-05,
      2.5104958695010282e-05,
      2.1170006220927462e-05,
      1.777081888576504e-05,
      1.5195196283457335e-05,
      1.2862983567174524e-05,
      1.0794463378260843e-05,
      9.127774319495074e-06,
      7.627656032127561e-06,
      6.453092282754369e-06,
      5.3729281717096455e-06,
      4.467122835194459e-06,
      3.7587954011542024e-06,
      3.091881808359176e-06,
      2.5507283680781256e-06,
      2.1290982203936437e-06,
      1.7369968645652989e-06,
      1.4134561752143782e-06,
      1.1253737284278031e-06,
      9.175020636575937e-07,
      7.408718829537975e-07,
      5.960260978099541e-07,
      4.776827040586795e-07,
      3.5698022315955313e-07,
      2.5765805844457645e-07,
      1.8108353572188207e-07,
      1.1398802257645002e-07,
      5.726591112420465e-08,
      1.8497486209412273e-08,
      2.6456359325521817e-09,
      1.0237382053190913e-09,
      6.3024194751903906e-09,
      1.599033616628276e-08,
      2.3310198216108802e-08,
      2.629170481327492e-08,
      2.562727274835197e-08,
      2.3446071750754527e-08,
      2.0410505285894942e-08,
      1.7076862590670316e-08,
      1.4043222584803061e-08,
      1.1437768066002718e-08,
      9.410320522817983e-09,
      7.736163709637367e-09,
      6.239730065971116e-09,
      4.997189329003504e-09,
      4.014341747904382e-09,
      3.204565501846446e-09,
      2.514152885879639e-09,
      2.015934308374767e-09,
      1.6191589180536425e-09,
      1.2888269340649572e-09,
      1.020401096951673e-09,
      8.061782352797309e-10,
      6.27535856612127e-10,
      4.959984090113778e-10,
      3.9508532556631337e-10,
      3.06449227105432e-10,
      2.332068704813395e-10,
      1.8215697006329634e-10,
      1.419207668051925e-10,
      1.096213675388924e-10,
      8.412084223641259e-11,
      6.542787145402684e-11,
      5.009166345604221e-11,
      3.7178336798060485e-11,
      2.9000350731944735e-11,
      2.2378900815800407e-11,
      1.743250162278276e-11,
      1.2982035585418217e-11,
      9.603261762192172e-12,
      8.079365301782993e-12,
      6.654711070391839e-12,
      4.1549264029328015e-12,
      3.0144406935883605e-12,
      2.1770142112631508e-12,
      1.60734706794452e-12,
      1.1786282670331327e-12,
      8.55843824629221e-13,
      6.211052180384036e-13,
      4.465835795781914e-13,
      3.275872682926423e-13,
      2.3520128986792566e-13,
      1.681520862221314e-13,
      1.1815648828274183e-13,
      8.312046797381845e-14,
      5.749241550499426e-14,
      4.020084436238795e-14,
      2.798482508280329e-14,
      1.937684428600199e-14,
      1.3323227713950541e-14,
      9.060287920305624e-15,
      6.2606991869961805e-15,
      4.262772504637835e-15,
      3.064619413274683e-15,
      2.176991564990273e-15,
      1.5499555205110167e-15,
      1.1545888104573239e-15,
      8.778333416175124e-16,
      7.048412617009249e-16,
      5.847957819491052e-16,
      5.067669480293615e-16,
      4.527653153892292e-16,
      4.0939087574270463e-16,
      3.7831773677047664e-16,
      3.570916205078759e-16,
      3.36465018283474e-16,
      3.1908845500790725e-16,
      3.0685589635123627e-16,
      2.9089922499306374e-16,
      2.8159750621301104e-16,
      2.658107179003222e-16,
      2.601453645023914e-16,
      2.463106959655481e-16,
      2.3982218536156377e-16,
      2.291810692638856e-16,
      2.2359917508103897e-16,
      2.1330143819924381e-16,
      2.101562989869702e-16,
      1.9917861964165645e-16,
      1.9671993445868343e-16,
      1.8868228000350977e-16,
      1.8649496300101334e-16,
      1.7965969828424676e-16,
      1.7556909824926992e-16,
      1.7423847566358242e-16,
      1.6850486993894866e-16,
      1.6795852045307984e-16,
      1.6348473065369904e-16,
      1.63802460653148e-16,
      1.6038977814355023e-16,
      1.6158926944109093e-16,
      1.594549846420265e-16,
      7.984874376392373e-17
    ],
    "eye": [
      0.00969336461275816,
      0.06469307094812393,
      0.12424357235431671,
      0.09184715896844864,
      0.05891313776373863,
      0.037808746099472046,
      0.02738264948129654,
      0.021201808005571365,
      0.017163779586553574,
      0.013986431062221527,
      0.011699643917381763,
      0.010486210696399212,
      0.00952419824898243,
      0.008762196637690067,
      0.007749625481665134,
      0.007375678047537804,
      0.007416152395308018,
      0.007364529650658369,
      0.00732377078384161,
      0.008105417713522911,
      0.009403688833117485,
      0.010485077276825905,
      0.011430221609771252,
      0.011460982263088226,
      0.010705468244850636,
      0.010320263914763927,
      0.00988202728331089,
      0.009269165806472301,
      0.007886783219873905,
      0.0065612029284238815,
      0.005783700384199619,
      0.0050111389718949795,
      0.00438260892406106,
      0.004110230598598719,
      0.003949543461203575,
      0.0036965326871722937,
      0.0035414493177086115,
      0.0034453177358955145,
      0.003372184932231903,
      0.003224937478080392,
      0.0029906705021858215,
      0.00281728059053421,
      0.0027927514165639877,
      0.0027591963298618793,
      0.0026022472884505987,
      0.0025175916962325573,
      0.0025101129431277514,
      0.0024564359337091446,
      0.0023798071779310703,
      0.002340170554816723,
      0.0022460641339421272,
      0.0021772042382508516,
      0.0021156365983188152,
      0.002071924274787307,
      0.002067842986434698,
      0.0020195201504975557,
      0.0019330712966620922,
      0.0018813831266015768,
      0.0017964554717764258,
      0.0017460801173001528,
      0.0016763190506026149,
      0.0016154433833435178,
      0.0015615561278536916,
      0.0015134606510400772,
      0.0014815818285569549,
      0.001416102983057499,
      0.0013973141321912408,
      0.0013592846225947142,
      0.00133059814106673,
      0.0012868172489106655,
      0.0012398832477629185,
      0.0012132527772337198,
      0.0011872292961925268,
      0.0011534637305885553,
      0.001099234796129167,
      0.0010344472248107195,
      0.0009843989973887801,
      0.0009571724804118276,
      0.0009119013557210565,
      0.0008902489789761603,
      0.0008707738015800714,
      0.0008461024845018983,
      0.0008054021163843572,
      0.0007800853345543146,
      0.0007849136018194258,
      0.0007783736800774932,
      0.0007381840259768069,
      0.0007132314494810998,
      0.0006977995508350432,
      0.0006857499247416854,
      0.0006535362335853279,
      0.0006364603177644312,
      0.0006215433240868151,
      0.0005904984427616,
      0.0005603518802672625,
      0.0005363125819712877,
      0.0005250390386208892,
      0.0005200756131671369,
      0.0005086561432108283,
      0.0004772789543494582,
      0.0004472145519685,
      0.0004254679079167545,
      0.0004145692219026387,
      0.0003877411363646388,
      0.00036135941627435386,
      0.00034370258799754083,
      0.0003179272171109915,
      0.0003004799655172974,
      0.00027231400599703193,
      0.00025128608103841543,
      0.000230671968893148,
      0.00020929850870743394,
      0.0001956941414391622,
      0.00017482490511611104,
      0.00015572767006233335,
      0.0001408124517183751,
      0.0001278712006751448,
      0.00011547332542249933,
      0.00010113047756021842,
      9.017156844493002e-05,
      8.158341370290145e-05,
      7.171885954448953e-05,
      6.083516564103775e-05,
      5.284975850372575e-05,
      4.6217315684771165e-05,
      3.832083166344091e-05,
      3.2807660318212584e-05,
      2.8244865461601876e-05,
      2.4057988412096165e-05,
      2.0189221686450765e-05,
      1.7200409274664707e-05,
      1.4343912880576681e-05,
      1.1921970326511655e-05,
      9.857747500063851e-06,
      8.38014511828078e-06,
      7.18436012903112e-06,
      5.907837476115674e-06,
      4.784702468896285e-06,
      4.042903128720354e-06,
      3.3295284538326086e-06,
      2.766329544101609e-06,
      2.2128631371742813e-06,
      1.7746755247571855e-06,
      1.462718500988558e-06,
      1.1508733450682485e-06,
      9.300204055762151e-07,
      7.735317808510445e-07,
      5.845565169693145e-07,
      4.253543011145666e-07,
      2.922548105743772e-07,
      1.8234851495435578e-07,
      9.363136399542782e-08,
      2.9776360932487478e-08,
      4.389303143170764e-09,
      2.0303789760589552e-09,
      1.1736366545278543e-08,
      2.7819078596280633e-08,
      3.8878546604337316e-08,
      4.129005048980616e-08,
      4.017169885628391e-08,
      3.682495020029819e-08,
      3.146199034631536e-08,
      2.6425675869745646e-08,
      2.186920866620312e-08,
      1.8069842511181378e-08,
      1.4829052652487462e-08,
      1.2137379101773149e-08,
      9.393971822646563e-09,
      7.859259909537286e-09,
      6.403809482691258e-09,
      4.993691238297515e-09,
      3.916727830954869e-09,
      3.0222957470016354e-09,
      2.3902024803845734e-09,
      1.923845305284999e-09,
      1.5120400487234065e-09,
      1.2035004104404834e-09,
      9.627896258024293e-10,
      7.545903346617422e-10,
      5.923425083764755e-10,
      4.476882753401412e-10,
      3.4933153592042743e-10,
      2.7472549235518784e-10,
      2.1296249486102425e-10,
      1.6657278334442083e-10,
      1.2644127411753914e-10,
      9.660326705240863e-11,
      7.519097150465726e-11,
      5.7635937689148875e-11,
      4.263844138874262e-11,
      3.3123309650662236e-11,
      2.478623382928813e-11,
      1.892022996607956e-11,
      1.4372546555674326e-11,
      1.0488069614178475e-11,
      7.979471250418868e-12,
      6.014951557664627e-12,
      4.485426786937641e-12,
      3.3366759875919083e-12,
      2.486614863669856e-12,
      1.790373405086143e-12,
      1.3236604737634772e-12,
      9.452269696119675e-13,
      6.766077498623901e-13,
      4.671980033746359e-13,
      3.360564864579585e-13,
      2.4655402502613e-13,
      1.784872976414581e-13,
      1.2521590481064798e-13,
      8.5106692472494e-14,
      5.930495759190121e-14,
      4.155176026930489e-14,
      2.816724718052166e-14,
      1.890838593825942e-14,
      1.2734289093856415e-14,
      8.78978879563291e-15,
      6.146726668778378e-15,
      4.274955379518193e-15,
      2.8129631717883517e-15,
      1.9588943453576835e-15,
      1.4035045827219322e-15,
      1.0419318402857258e-15,
      7.914344986899161e-16,
      6.57559406129157e-16,
      5.339763991522482e-16,
      4.63011237677454e-16,
      4.081407345218961e-16,
      3.766404262464559e-16,
      3.450571352119644e-16,
      3.2674303881268516e-16,
      3.057679619398269e-16,
      2.912478584601977e-16,
      2.762401551705256e-16,
      2.633713424215686e-16,
      2.5210461308300435e-16,
      2.402191261764708e-16,
      2.313288007109877e-16,
      2.208230510661926e-16,
      2.1223004740008553e-16,
      2.0358991429139764e-16,
      1.9596526780734925e-16,
      1.8915652580974357e-16,
      1.8214652084293638e-16,
      1.7650387851590385e-16,
      1.7111291085332425e-16,
      1.6534388856358342e-16,
      1.6062369158589043e-16,
      1.5668416781799028e-16,
      1.527456234319354e-16,
      1.4961553228936533e-16,
      1.4688857589012912e-16,
      1.4462378184273853e-16,
      1.431179425509776e-16,
      1.4068984319833434e-16,
      1.3979650137166687e-16,
      1.3966048640918355e-16,
      6.940236583477524e-17
    ],
    "muscle": [
      0.01732015609741211,
      0.11410730332136154,
      0.19465051591396332,
      0.1263016015291214,
      0.07383710145950317,
      0.0514233224093914,
      0.03893675282597542,
      0.028582466766238213,
      0.022277509793639183,
      0.017797132954001427,
      0.015415066853165627,
      0.01378651987761259,
      0.013361877761781216,
      0.01250836905092001,
      0.010829873383045197,
      0.009771411307156086,
      0.009307648055255413,
      0.009123161435127258,
      0.009045634418725967,
      0.008937941864132881,
      0.009195572696626186,
      0.009785857982933521,
      0.009609217755496502,
      0.008610464632511139,
      0.00773185770958662,
      0.007313207723200321,
      0.007156698498874903,
      0.006796661764383316,
      0.006268344819545746,
      0.005761832930147648,
      0.005339706316590309,
      0.005063115153461695,
      0.004885168746113777,
      0.004832015372812748,
      0.0048031285405159,
      0.00469864159822464,
      0.004645558539777994,
      0.004640817176550627,
      0.004657088778913021,
      0.004624344874173403,
      0.004408099222928286,
      0.004280733410269022,
      0.004236541222780943,
      0.004222487565129995,
      0.004037691280245781,
      0.00402152119204402,
      0.0041466341353952885,
      0.004152697045356035,
      0.00405979435890913,
      0.004065480083227158,
      0.004020661115646362,
      0.003947912715375423,
      0.003950478509068489,
      0.003983503673225641,
      0.003818108467385173,
      0.0036287251859903336,
      0.003566211322322488,
      0.0035952816251665354,
      0.003456134581938386,
      0.003390050493180752,
      0.003330675885081291,
      0.0032715792767703533,
      0.0031896166037768126,
      0.0031502896454185247,
      0.003136205952614546,
      0.0031275844667106867,
      0.003219140926375985,
      0.0032460649963468313,
      0.0030613287817686796,
      0.0029901110101491213,
      0.0030517945997416973,
      0.0031145934481173754,
      0.003082991112023592,
      0.0030187785159796476,
      0.0029923419933766127,
      0.003016159636899829,
      0.0030245473608374596,
      0.002973914844915271,
      0.003015222493559122,
      0.0030859087128192186,
      0.0030907464679330587,
      0.003008423140272498,
      0.0029872884042561054,
      0.0029850355349481106,
      0.0030075907707214355,
      0.0030493459198623896,
      0.0030201764311641455,
      0.0030015164520591497,
      0.002957645570859313,
      0.0028747969772666693,
      0.0028453136328607798,
      0.0027928492054343224,
      0.0027168423403054476,
      0.0026640768628567457,
      0.0026152513455599546,
      0.0025624390691518784,
      0.002573458245024085,
      0.0024706386029720306,
      0.0023448276333510876,
      0.002255902858451009,
      0.00217550341039896,
      0.0021052276715636253,
      0.0019761703442782164,
      0.001851686043664813,
      0.0017706973012536764,
      0.001716304337605834,
      0.0016579256625846028,
      0.0015371658373624086,
      0.0013979269424453378,
      0.001326703350059688,
      0.0012291058665141463,
      0.0011181238805875182,
      0.0010268251644447446,
      0.0009297357173636556,
      0.0008890299359336495,
      0.0007948691491037607,
      0.0006955627468414605,
      0.0006239830399863422,
      0.0005610561347566545,
      0.000492328021209687,
      0.0004380367463454604,
      0.0003902618191204965,
      0.0003412748919799924,
      0.00029983013519085944,
      0.0002621296443976462,
      0.00022650652681477368,
      0.0001987130381166935,
      0.0001672248909017071,
      0.0001438965555280447,
      0.00012308949953876436,
      0.00010006797674577683,
      8.64313478814438e-05,
      7.430381083395332e-05,
      6.168640538817272e-05,
      5.251510447124019e-05,
      4.429063483257778e-05,
      3.678317443700507e-05,
      3.149668191326782e-05,
      2.566833791206591e-05,
      2.1404383005574346e-05,
      1.7988702893489972e-05,
      1.4462885701505002e-05,
      1.1785047718149144e-05,
      9.54584902501665e-06,
      7.832017217879184e-06,
      6.171325367176905e-06,
      4.867069492320297e-06,
      3.8757843867642805e-06,
      2.9051091132714646e-06,
      2.0349320948298555e-06,
      1.273144562219386e-06,
      6.504500902337895e-07,
      2.1964741847568803e-07,
      3.505905610268201e-08,
      1.4710058060529718e-08,
      7.740167262682007e-08,
      1.8690066383442172e-07,
      2.722105989505508e-07,
      2.9703693371629925e-07,
      2.949184647604852e-07,
      2.7650401079881703e-07,
      2.3304164642468095e-07,
      1.946296777077805e-07,
      1.621407506036121e-07,
      1.3387405317644152e-07,
      1.1000977195863015e-07,
      8.871398904375383e-08,
      7.05941047840497e-08,
      5.634105448848459e-08,
      4.398787822879058e-08,
      3.4690934569425735e-08,
      2.775807672605879e-08,
      2.2453955139667414e-08,
      1.7562010512506276e-08,
      1.3548139499164336e-08,
      1.1230833152353625e-08,
      8.75061090255258e-09,
      6.899390836423436e-09,
      5.467744035314581e-09,
      4.3528034510131874e-09,
      3.4073313059934662e-09,
      2.670614840383223e-09,
      2.0088399832474124e-09,
      1.5575608580675748e-09,
      1.2335252819184461e-09,
      9.632786790447767e-10,
      7.481774089157511e-10,
      5.595207075437258e-10,
      4.2790787579960465e-10,
      3.3633351659290156e-10,
      2.560500977910607e-10,
      1.864401966145124e-10,
      1.4217695076812475e-10,
      1.078060210546461e-10,
      8.104807797115754e-11,
      6.209854852556873e-11,
      4.6356158495131083e-11,
      3.364348036272169e-11,
      2.4064167325477115e-11,
      1.7544143221526198e-11,
      1.296952562707121e-11,
      9.4020780744275e-12,
      7.0074787986151854e-12,
      5.129092463251883e-12,
      3.692365857510538e-12,
      2.606815588043765e-12,
      1.830698353327831e-12,
      1.2769403590073836e-12,
      8.945529863732538e-13,
      6.403356035515617e-13,
      4.4251421645914724e-13,
      3.047074311618436e-13,
      2.083449244291019e-13,
      1.4657480958135682e-13,
      9.683925075677433e-14,
      6.489551734531473e-14,
      4.356562175898346e-14,
      2.907695717774099e-14,
      1.8977795206089228e-14,
      1.2776772878358902e-14,
      8.696050200459118e-15,
      6.005544487679452e-15,
      4.237918016866552e-15,
      3.0816911505683565e-15,
      2.304251912568127e-15,
      1.8225804861231017e-15,
      1.536748688676546e-15,
      1.3349456300920507e-15,
      1.2003364246638182e-15,
      1.1060772218648204e-15,
      1.0358923894926843e-15,
      9.711403205651188e-16,
      9.304468460757725e-16,
      8.89052134185218e-16,
      8.496188859027085e-16,
      8.207073750118735e-16,
      7.89719468729963e-16,
      7.583365803968359e-16,
      7.3538145813065235e-16,
      7.102629607776221e-16,
      6.878030351482271e-16,
      6.686748077377384e-16,
      6.480289619835661e-16,
      6.310229756224231e-16,
      6.125689864379489e-16,
      6.024563659597982e-16,
      5.855529235248322e-16,
      5.751976281072931e-16,
      5.642183870449829e-16,
      5.55325123433964e-16,
      5.45726757833915e-16,
      5.418350649577552e-16,
      5.34342052687666e-16,
      5.307378745575398e-16,
      5.26205665954578e-16,
      5.277212196554528e-16,
      2.6233012717115627e-16
    ],
    "chewing": [
      0.007538279052823782,
      0.0450853556394577,
      0.09317152202129364,
      0.09084462374448776,
      0.08131852746009827,
      0.05479215085506439,
      0.03729954734444618,
      0.02733883634209633,
      0.020359978079795837,
      0.01655394397675991,
      0.013003752566874027,
      0.010994979180395603,
      0.010261684656143188,
      0.00842713750898838,
      0.007249024696648121,
      0.005999981891363859,
      0.005385261960327625,
      0.005148567724972963,
      0.00521158566698432,
      0.005134637467563152,
      0.004671229515224695,
      0.00510105537250638,
      0.006196519359946251,
      0.007593127433210611,
      0.006355754565447569,
      0.00495000509545207,
      0.004541526082903147,
      0.004309029784053564,
      0.003904864192008972,
      0.0035901700612157583,
      0.00350165949203074,
      0.003175613470375538,
      0.0031996616162359715,
      0.0031742341816425323,
      0.0027997593861073256,
      0.002779698930680752,
      0.0027932135853916407,
      0.0027782905381172895,
      0.0026151034981012344,
      0.002477891743183136,
      0.002565313596278429,
      0.002537565305829048,
      0.002509406069293618,
      0.0025209286250174046,
      0.0023995169904083014,
      0.0024396434891968966,
      0.002534967614337802,
      0.0025462862104177475,
      0.0024589677341282368,
      0.002644736086949706,
      0.00259277387522161,
      0.0026356910821050406,
      0.002750326646491885,
      0.002726336009800434,
      0.002533462131395936,
      0.0025950344279408455,
      0.002659606048837304,
      0.0026247079949826,
      0.002531158970668912,
      0.002655311953276396,
      0.0026764273643493652,
      0.002464987337589264,
      0.0027169049717485905,
      0.0029253573156893253,
      0.002790638944134116,
      0.0025655205827206373,
      0.0024523946922272444,
      0.002508462406694889,
      0.002966590691357851,
      0.0024689834099262953,
      0.002238607732579112,
      0.0024515255354344845,
      0.002708570333197713,
      0.0025044665671885014,
      0.002411783207207918,
      0.0023038885556161404,
      0.0023102620616555214,
      0.002439031610265374,
      0.002396766096353531,
      0.00235161604359746,
      0.0025170997250825167,
      0.0028281924314796925,
      0.003233898663893342,
      0.0027529422659426928,
      0.002652097260579467,
      0.0027518633287400007,
      0.0026568544562906027,
      0.002525058574974537,
      0.0022753560915589333,
      0.0022649578750133514,
      0.0021510464139282703,
      0.0023421619553118944,
      0.0026660386938601732,
      0.002278899075463414,
      0.0020084280986338854,
      0.0021190971601754427,
      0.002346823224797845,
      0.0021888716146349907,
      0.0020319069735705853,
      0.0018966452917084098,
      0.0021716670598834753,
      0.0023925229907035828,
      0.0019303013104945421,
      0.0017506190342828631,
      0.0016126363771036267,
      0.0016510328277945518,
      0.0014472318580374122,
      0.0013159686932340264,
      0.0012887712800875306,
      0.0011625170009210706,
      0.001146661932580173,
      0.0010905421804636717,
      0.0009529715171083808,
      0.0009903984609991312,
      0.0007369068916887045,
      0.0006919536390341818,
      0.0006346675218082964,
      0.000543723814189434,
      0.0005714985309168696,
      0.00047370477113872766,
      0.000444636243628338,
      0.00047646817984059453,
      0.0003635766915977001,
      0.0002932282804977149,
      0.0002560455468483269,
      0.00022159508080221713,
      0.00018475682009011507,
      0.0001559423399157822,
      0.00012242706725373864,
      0.0001129378579207696,
      0.00010298239067196846,
      8.819132199278101e-05,
      7.32756670913659e-05,
      6.216340261744335e-05,
      4.576733408612199e-05,
      3.831875801552087e-05,
      3.268531509093009e-05,
      2.8680477043963037e-05,
      2.595638216007501e-05,
      1.9805522242677398e-05,
      1.4728692804055754e-05,
      1.2196393072372302e-05,
      1.1358036317687947e-05,
      8.813439308141824e-06,
      7.4170748121105134e-06,
      5.264739684207598e-06,
      4.026378519483842e-06,
      3.527793069224572e-06,
      2.603166876724572e-06,
      1.831683334785339e-06,
      1.189132717627217e-06,
      5.331030479283072e-07,
      1.651232253152557e-07,
      2.402249066335571e-08,
      1.0851156417857055e-08,
      6.279503139694498e-08,
      1.3221365691151732e-07,
      2.0756080232331442e-07,
      2.4510228513463517e-07,
      2.991714040945226e-07,
      2.695439320632431e-07,
      1.9336935963565338e-07,
      1.5860368307585304e-07,
      1.1767627228209676e-07,
      1.137856671107329e-07,
      1.0358367319440731e-07,
      7.937128998491971e-08,
      6.21417655111145e-08,
      4.660991592686514e-08,
      3.6074268905395e-08,
      2.8356490489045427e-08,
      2.0953082824348712e-08,
      1.6765111965355572e-08,
      1.289871320864222e-08,
      1.0290571950122285e-08,
      9.857088478781861e-09,
      8.838567211455484e-09,
      6.76864342352701e-09,
      5.1136614942493e-09,
      3.812533844183008e-09,
      2.8965272402814435e-09,
      2.3689781247782093e-09,
      1.8347415808861456e-09,
      1.3025093226204376e-09,
      9.989392646403417e-10,
      7.286103942405475e-10,
      5.316111995057327e-10,
      4.1539124917555625e-10,
      3.365390466303353e-10,
      2.4476765059233685e-10,
      1.847875602534188e-10,
      1.366782936829125e-10,
      1.1018867762668805e-10,
      8.355158925832384e-11,
      5.6676073556527484e-11,
      4.046777843380589e-11,
      3.364088868584858e-11,
      2.625998724026246e-11,
      1.9656529876010964e-11,
      1.4014192584177465e-11,
      9.399487264916129e-12,
      7.147132278367829e-12,
      5.516758057322324e-12,
      4.255687816034914e-12,
      2.8027920696144237e-12,
      1.9685967266036553e-12,
      1.5019435348206933e-12,
      1.0152482153580333e-12,
      7.014755529916039e-13,
      4.5446960539492764e-13,
      3.0469859491413787e-13,
      2.1464792020631923e-13,
      1.5194161033516007e-13,
      1.0044310489679825e-13,
      6.801387930502681e-14,
      4.6713202967244016e-14,
      3.0778246569223774e-14,
      2.066149172325754e-14,
      1.462575347562379e-14,
      1.01511774179097e-14,
      6.604498425341913e-15,
      4.54208161899494e-15,
      3.129049186165818e-15,
      2.31243382732213e-15,
      1.6454250275125225e-15,
      1.3779333991981537e-15,
      1.1625800369190762e-15,
      1.0115554388521737e-15,
      9.074134791410863e-16,
      8.627671665847002e-16,
      7.766958607098953e-16,
      7.497018735929664e-16,
      7.003007415871682e-16,
      6.873979945807619e-16,
      6.491743093469315e-16,
      6.330089502463792e-16,
      5.968027916137902e-16,
      5.848305102999427e-16,
      5.625570907376212e-16,
      5.40797026080895e-16,
      5.287316240824087e-16,
      5.10905815707442e-16,
      4.91934977606465e-16,
      4.90977142161798e-16,
      4.64775660246144e-16,
      4.591963071621391e-16,
      4.501591008896461e-16,
      4.397510776711405e-16,
      4.3278034062237244e-16,
      4.237352198857786e-16,
      4.1868023313568333e-16,
      4.119597943228289e-16,
      4.1279525997639727e-16,
      4.034536512384848e-16,
      4.06806895857987e-16,
      4.063458717066642e-16,
      1.9785213957647661e-16
    ],
    "shiver": [
      0.012938437052071095,
      0.08581018447875977,
      0.1759312003850937,
      0.13066883385181427,
      0.07477385550737381,
      0.03657048940658569,
      0.025576721876859665,
      0.021224074065685272,
      0.014887494035065174,
      0.010393979959189892,
      0.01010327972471714,
      0.009404398500919342,
      0.009702945128083229,
      0.010023696348071098,
      0.010063634254038334,
      0.01127531472593546,
      0.01346142590045929,
      0.01527626346796751,
      0.018731502816081047,
      0.02644309587776661,
      0.034012746065855026,
      0.03289486840367317,
      0.02636510692536831,
      0.020589763298630714,
      0.017774393782019615,
      0.02128269337117672,
      0.019958769902586937,
      0.015716783702373505,
      0.011407677084207535,
      0.010036695748567581,
      0.009277082048356533,
      0.01124765444546938,
      0.01155079435557127,
      0.011072899214923382,
      0.012247264385223389,
      0.011589514091610909,
      0.011329477652907372,
      0.01276619452983141,
      0.012913522310554981,
      0.010925202630460262,
      0.012192237190902233,
      0.01284372340887785,
      0.012880177237093449,
      0.010880505666136742,
      0.009064177051186562,
      0.008383458480238914,
      0.009186804294586182,
      0.009904846549034119,
      0.009724480099976063,
      0.008597483858466148,
      0.009048212319612503,
      0.011494861915707588,
      0.010667757131159306,
      0.008583410643041134,
      0.009277289733290672,
      0.008999703451991081,
      0.008567793294787407,
      0.008451136760413647,
      0.009710079990327358,
      0.010484381578862667,
      0.01134529896080494,
      0.01174674741923809,
      0.011130993254482746,
      0.011660158634185791,
      0.011988217011094093,
      0.013355150818824768,
      0.012239129282534122,
      0.010606405325233936,
      0.009768792428076267,
      0.009606986306607723,
      0.011156246066093445,
      0.012190097011625767,
      0.01226955559104681,
      0.011881526559591293,
      0.010677315294742584,
      0.011703447438776493,
      0.010981006547808647,
      0.010671715252101421,
      0.01028653047978878,
      0.009325866587460041,
      0.009336007758975029,
      0.009646521881222725,
      0.010921123437583447,
      0.009547940455377102,
      0.010241221636533737,
      0.011771912686526775,
      0.010095801204442978,
      0.011517980135977268,
      0.013331024907529354,
      0.011374847032129765,
      0.01099922601133585,
      0.014904571697115898,
      0.01553476694971323,
      0.013224229216575623,
      0.01016382034868002,
      0.00919509306550026,
      0.011181715875864029,
      0.011331216432154179,
      0.011137736961245537,
      0.009626468643546104,
      0.009107820689678192,
      0.009436242282390594,
      0.006920697633177042,
      0.006015373859554529,
      0.006079192738980055,
      0.005567855201661587,
      0.0055028898641467094,
      0.005981877911835909,
      0.005792641080915928,
      0.005270425230264664,
      0.004512476269155741,
      0.004367433022707701,
      0.003830807050690055,
      0.0031186712440103292,
      0.0028102430514991283,
      0.002670483896508813,
      0.0026255615521222353,
      0.002220296300947666,
      0.0021354351192712784,
      0.0021213816944509745,
      0.0019342125160619617,
      0.001263178652152419,
      0.0010711380746215582,
      0.0009210345451720059,
      0.0007598910597153008,
      0.0008560019196011126,
      0.0008005223353393376,
      0.0006461050943471491,
      0.0006521295290440321,
      0.0004516059998422861,
      0.00034099892945960164,
      0.00031159556237980723,
      0.00037495922879315913,
      0.0003357334353495389,
      0.00017147981270682067,
      0.0001254083908861503,
      9.045223123393953e-05,
      9.737871732795611e-05,
      0.00010721310536609963,
      7.458126492565498e-05,
      5.680157846654765e-05,
      3.892673339578323e-05,
      3.138522879453376e-05,
      3.443009700276889e-05,
      2.888620292651467e-05,
      2.513848085072823e-05,
      2.0335899534984492e-05,
      1.0961407497234177e-05,
      7.36346555640921e-06,
      4.876783350482583e-06,
      4.170161446381826e-06,
      2.246232952529681e-06,
      4.728455564873002e-07,
      6.50210907338078e-08,
      2.027263690251857e-08,
      1.5143351106416958e-07,
      3.9178203792289423e-07,
      5.537246465792123e-07,
      7.286197387657012e-07,
      8.292778943541634e-07,
      8.511715918757545e-07,
      6.209688194758201e-07,
      5.318156013345288e-07,
      4.792063919012435e-07,
      6.000015559948224e-07,
      5.589307079389982e-07,
      2.1919019843608112e-07,
      1.8565542347914743e-07,
      2.0885624962829752e-07,
      1.3194612336064893e-07,
      8.665232797966382e-08,
      6.576948408110184e-08,
      4.9799176338183315e-08,
      4.072422044032464e-08,
      3.3425134660092226e-08,
      2.5425789473842997e-08,
      1.646873215577216e-08,
      1.8417756209032632e-08,
      1.969803875567777e-08,
      1.4345871157672718e-08,
      1.079566835926471e-08,
      6.811631259040496e-09,
      4.740236647648999e-09,
      3.8145318015381235e-09,
      2.5327555608356533e-09,
      2.128057285943896e-09,
      1.860386622531962e-09,
      1.4074897913829432e-09,
      1.0235675640402064e-09,
      8.186965549938918e-10,
      6.225397974901625e-10,
      4.858133340057691e-10,
      3.547087901178969e-10,
      2.900284734597136e-10,
      2.7185420581332664e-10,
      1.8417570246676007e-10,
      9.985041959925667e-11,
      7.740777463460802e-11,
      5.1674556994507626e-11,
      3.417588087528678e-11,
      3.5867159936531223e-11,
      2.6224042035116746e-11,
      1.6020301404906512e-11,
      9.939556122606774e-12,
      7.687517289411971e-12,
      5.397093362502492e-12,
      3.422479747522411e-12,
      2.906108513556216e-12,
      3.1674313779456176e-12,
      2.0696157461419507e-12,
      1.17902400082609e-12,
      7.144976884448928e-13,
      5.782698538764341e-13,
      3.4681610881770464e-13,
      2.4670955382777304e-13,
      1.437087211383914e-13,
      9.197734262590684e-14,
      7.449466390974102e-14,
      5.354008184607455e-14,
      3.3201336780775206e-14,
      2.0998844617358195e-14,
      1.4864001820829795e-14,
      9.489792916869862e-15,
      8.284801305007052e-15,
      6.488880545624069e-15,
      4.51195562167642e-15,
      4.275897703672014e-15,
      3.729635568075875e-15,
      3.4144753607097574e-15,
      3.0800532006066035e-15,
      2.926443775622036e-15,
      2.7715127674815153e-15,
      2.6387153655274597e-15,
      2.479323670128461e-15,
      2.436735488815225e-15,
      2.341746884769523e-15,
      2.233260175434613e-15,
      2.135926772432674e-15,
      2.1135502795485836e-15,
      1.99835570454613e-15,
      1.9801663072785544e-15,
      1.884234108529611e-15,
      1.8523193893847266e-15,
      1.815250051239326e-15,
      1.7353388454129873e-15,
      1.7246685596181881e-15,
      1.692767710637815e-15,
      1.6287816771319227e-15,
      1.6513908923182713e-15,
      1.5439834088372818e-15,
      1.604050856170939e-15,
      1.5496539767817941e-15,
      1.5127357281383602e-15,
      1.5281117054716307e-15,
      1.5462387399384648e-15,
      1.4826328124676528e-15,
      7.638705113390443e-16
    ],
    "electrode": [
      0.055927574634552,
      0.3087612986564636,
      0.4284334182739258,
      0.252246230840683,
      0.1654941290616989,
      0.09593440592288971,
      0.07010971009731293,
      0.04967774450778961,
      0.044656362384557724,
      0.03723910450935364,
      0.029231315478682518,
      0.02631099335849285,
      0.020882142707705498,
      0.02008388377726078,
      0.018220607191324234,
      0.017402980476617813,
      0.016403434798121452,
      0.01406047958880663,
      0.014474316500127316,
      0.013456574641168118,
      0.01479476410895586,
      0.014662784524261951,
      0.013170454651117325,
      0.012394092977046967,
      0.011303053237497807,
      0.011078390292823315,
      0.010306631214916706,
      0.009600529447197914,
      0.009034392423927784,
      0.008332030847668648,
      0.008313419297337532,
      0.008072415366768837,
      0.00763916177675128,
      0.007145319599658251,
      0.006623325403779745,
      0.006769378669559956,
      0.006663303356617689,
      0.006632480304688215,
      0.006346730515360832,
      0.005989373661577702,
      0.006326879840344191,
      0.00622204877436161,
      0.0057699535973370075,
      0.0052603064104914665,
      0.005115669220685959,
      0.00516674667596817,
      0.00497382041066885,
      0.0048813060857355595,
      0.004576267208904028,
      0.004490267485380173,
      0.004407728556543589,
      0.004374117124825716,
      0.004535956308245659,
      0.004319497384130955,
      0.004309253767132759,
      0.004097128286957741,
      0.003963255323469639,
      0.003957906272262335,
      0.0036777097266167402,
      0.0035965184215456247,
      0.003450334072113037,
      0.003430767683312297,
      0.003469724440947175,
      0.003369644284248352,
      0.003473630640655756,
      0.00332442345097661,
      0.003131693694740534,
      0.003009782638400793,
      0.00299866427667439,
      0.003036427777260542,
      0.0029006830882281065,
      0.003006929764524102,
      0.0028569852001965046,
      0.0028431075625121593,
      0.0027861599810421467,
      0.002677032258361578,
      0.002681866753846407,
      0.0026890411972999573,
      0.0026486492715775967,
      0.002619598526507616,
      0.0025117374025285244,
      0.002530944300815463,
      0.002483225194737315,
      0.0024059112183749676,
      0.0023356794845312834,
      0.002306995913386345,
      0.0022388403303921223,
      0.002039143117144704,
      0.0020345342345535755,
      0.0019570710137486458,
      0.001931112608872354,
      0.0019687567837536335,
      0.0019868980161845684,
      0.001986348768696189,
      0.0019312084186822176,
      0.0018304099794477224,
      0.0016719703562557697,
      0.001540650730021298,
      0.0015253042802214622,
      0.001432139310054481,
      0.0013862670166417956,
      0.0013079674681648612,
      0.0012852934887632728,
      0.0012032692320644855,
      0.00112551124766469,
      0.0011008556466549635,
      0.0010484801605343819,
      0.0010041523491963744,
      0.0009336910443380475,
      0.0008442634716629982,
      0.0007803155458532274,
      0.0007622652337886393,
      0.0013178064255043864,
      0.0011498227249830961,
      0.0005563449230976403,
      0.0004633501230273396,
      0.0004116196068935096,
      0.0003637302725110203,
      0.0003264375263825059,
      0.00030123497708700597,
      0.0002582389861345291,
      0.00022398607688955963,
      0.00019576620252337307,
      0.00017381190264131874,
      0.0001601356198079884,
      0.00012971871183253825,
      0.00010359239240642637,
      8.607965719420463e-05,
      7.58264068281278e-05,
      6.535223656101152e-05,
      5.56232625967823e-05,
      4.716943658422679e-05,
      3.853436646750197e-05,
      3.182386717526242e-05,
      2.712869354581926e-05,
      2.2709573386237025e-05,
      1.9208764570066705e-05,
      1.577674447617028e-05,
      1.2722758583549876e-05,
      1.0525879588385578e-05,
      8.656162208353635e-06,
      6.900575044710422e-06,
      5.940226401435211e-06,
      4.919276307191467e-06,
      3.831724370684242e-06,
      3.0149669782986166e-06,
      2.268646539960173e-06,
      1.703469138192304e-06,
      1.281738946090627e-06,
      9.146829711426108e-07,
      6.051649279470439e-07,
      3.1934922617438133e-07,
      1.0675851314090323e-07,
      1.680626304789712e-08,
      6.813677622119485e-09,
      3.938871984132675e-08,
      9.609014739453414e-08,
      1.328649261722603e-07,
      1.4464681896697584e-07,
      1.2704902019322617e-07,
      1.0943892192472049e-07,
      9.593252059403312e-08,
      7.974222171469592e-08,
      6.473033664633476e-08,
      5.2996412591710396e-08,
      4.5029530326701206e-08,
      3.8310712824340953e-08,
      3.111315294290762e-08,
      2.3691614003951145e-08,
      1.8403492063612248e-08,
      1.5223051264001697e-08,
      1.1757290252489838e-08,
      8.792467198759368e-09,
      7.066148999257393e-09,
      5.778160172553726e-09,
      4.474417281130627e-09,
      3.5852010249470823e-09,
      2.7735407304163573e-09,
      2.125528419938405e-09,
      1.6966609228674656e-09,
      1.2973649932135345e-09,
      9.720555471659509e-10,
      7.633465526346583e-10,
      6.231177795967824e-10,
      5.003958913896156e-10,
      3.6603792219480624e-10,
      2.6974616984531963e-10,
      2.0589678573212922e-10,
      1.5339872427855283e-10,
      1.1628539797747806e-10,
      9.522133082029427e-11,
      7.912158428435845e-11,
      5.707708958246904e-11,
      4.334155950802554e-11,
      1.0045975856742828e-10,
      1.2596765297523405e-10,
      2.6129506544569914e-11,
      1.2916163798226687e-11,
      9.46989014982691e-12,
      6.845562311452724e-12,
      4.931774606753425e-12,
      3.6291252121511963e-12,
      2.648593584037018e-12,
      1.904058941765152e-12,
      1.4042596295851806e-12,
      1.0393768094460465e-12,
      7.088675349833928e-13,
      4.847966104080947e-13,
      3.2005553264082e-13,
      2.3073459375771987e-13,
      1.5397458427626048e-13,
      1.0709492917048563e-13,
      7.774336729937659e-14,
      5.268372476013687e-14,
      3.543649748638522e-14,
      2.3831119505069234e-14,
      1.7366038891197116e-14,
      1.165082129893618e-14,
      8.274835115349658e-15,
      6.041903376940343e-15,
      4.03236260232572e-15,
      3.2246938172291687e-15,
      2.378547501712407e-15,
      1.904620921020601e-15,
      1.64182259638785e-15,
      1.4301598625390778e-15,
      1.279668259954235e-15,
      1.1680356702532227e-15,
      1.0940773061010687e-15,
      1.0290309991034508e-15,
      9.644233492933922e-16,
      9.240215717752566e-16,
      8.807447526759031e-16,
      8.389357357950229e-16,
      8.082401088194743e-16,
      7.668858956917104e-16,
      7.44133849574631e-16,
      7.079982593744601e-16,
      6.870554226931567e-16,
      6.515990999771246e-16,
      6.405110151810921e-16,
      6.063651583135808e-16,
      5.792730212538888e-16,
      5.770687238877779e-16,
      5.474674634800818e-16,
      5.352407546447028e-16,
      5.170634805361847e-16,
      5.124304750124997e-16,
      4.978210095569352e-16,
      4.799839779954173e-16,
      4.781982737239276e-16,
      4.718119629389854e-16,
      4.608787792931821e-16,
      4.593215092196551e-16,
      4.566827898307211e-16,
      4.502327398164981e-16,
      2.2717905395349086e-16
    ]
  },
  "band_power_overall": {
    "delta": 0.05683813616633415,
    "theta": 0.011041661724448204,
    "alpha": 0.008286667056381702,
    "beta": 0.0026722995098680258
  },
  "cov_mean": [
    [
      0.8764964322346632,
      0.6826658323374731,
      0.280915376273171,
      0.2214442724382016,
      0.16451857686803956,
      0.1359139653227548,
      0.13633075943807285,
      0.12328102321214163
    ],
    [
      0.6826658323374731,
      0.8781775256975304,
      0.20661361147270146,
      0.31107970369598975,
      0.1279782996857884,
      0.19719356822003611,
      0.14561011875283375,
      0.16134960941742058
    ],
    [
      0.280915376273171,
      0.20661361147270146,
      0.8033198152367078,
      0.2861967523097677,
      0.5000003687615516,
      0.25696404461226136,
      0.352799713983012,
      0.28029271094502334
    ],
    [
      0.2214442724382016,
      0.31107970369598975,
      0.2861967523097677,
      0.8186989983302068,
      0.2915606667980912,
      0.5263105206386273,
      0.30317443901379354,
      0.3820539911202917
    ],
    [
      0.16451857686803956,
      0.1279782996857884,
      0.5000003687615516,
      0.2915606667980912,
      0.8146161771585301,
      0.41156797193832123,
      0.5570863060782634,
      0.4788729513343828
    ],
    [
      0.1359139653227548,
      0.19719356822003611,
      0.25696404461226136,
      0.5263105206386273,
      0.41156797193832123,
      0.8279285193839678,
      0.46482615766012053,
      0.5649861927210175
    ],
    [
      0.13633075943807285,
      0.14561011875283375,
      0.352799713983012,
      0.30317443901379354,
      0.5570863060782634,
      0.46482615766012053,
      0.8428070794011523,
      0.6244357295882064
    ],
    [
      0.12328102321214163,
      0.16134960941742058,
      0.28029271094502334,
      0.3820539911202917,
      0.4788729513343828,
      0.5649861927210175,
      0.6244357295882064,
      0.8428414433838395
    ]
  ],
  "acf_mean": [
    1.0,
    0.9653046131134033,
    0.8753570914268494,
    0.7795111536979675,
    0.7053356766700745,
    0.6460167169570923,
    0.5865764021873474,
    0.5272199511528015,
    0.47856199741363525,
    0.44565775990486145,
    0.42466050386428833,
    0.4110162556171417,
    0.4044191539287567,
    0.40599295496940613,
    0.4146197438240051,
    0.42732006311416626,
    0.44157636165618896,
    0.4562391936779022,
    0.47069624066352844,
    0.4838007688522339,
    0.49353694915771484,
    0.4975448250770569,
    0.4940985143184662,
    0.48275673389434814,
    0.4641437828540802,
    0.43924325704574585,
    0.40905794501304626,
    0.37478816509246826,
    0.3379814028739929,
    0.30038735270500183,
    0.26376140117645264,
    0.22975771129131317,
    0.1997561752796173,
    0.1746130883693695,
    0.15461568534374237,
    0.1397894322872162,
    0.1302253007888794,
    0.1259845495223999,
    0.12666627764701843,
    0.13118113577365875,
    0.13799110054969788,
    0.14549988508224487,
    0.15227511525154114,
    0.15713168680667877,
    0.15918560326099396,
    0.15780103206634521,
    0.15239669382572174,
    0.1423119604587555,
    0.12696483731269836,
    0.10625199973583221,
    0.08084814995527267,
    0.052099358290433884,
    0.02156444638967514,
    -0.009414770640432835,
    -0.03982209414243698,
    -0.06879111379384995,
    -0.09536874294281006,
    -0.11843976378440857,
    -0.13695508241653442,
    -0.15039077401161194,
    -0.1590670794248581,
    -0.16395992040634155,
    -0.16608481109142303,
    -0.16600966453552246,
    -0.1639416366815567,
    -0.16024422645568848,
    -0.15581388771533966,
    -0.1519816368818283,
    -0.15010160207748413,
    -0.1512138545513153,
    -0.1560191810131073,
    -0.16507171094417572,
    -0.17887121438980103,
    -0.1976315677165985,
    -0.2208804488182068,
    -0.2473551481962204,
    -0.2754332423210144,
    -0.30375996232032776,
    -0.33144813776016235,
    -0.35773327946662903,
    -0.38165950775146484,
    -0.40227529406547546,
    -0.419077068567276,
    -0.43212929368019104,
    -0.44174474477767944,
    -0.44810718297958374,
    -0.45118579268455505,
    -0.4510279595851898,
    -0.44827255606651306,
    -0.44434866309165955,
    -0.4408993721008301,
    -0.43885642290115356,
    -0.43827107548713684,
    -0.43919625878334045,
    -0.4424758851528168,
    -0.44943001866340637,
    -0.4609231650829315,
    -0.47701969742774963,
    -0.4973682761192322,
    -0.5214938521385193,
    -0.5486433506011963,
    -0.5776943564414978,
    -0.6075024604797363,
    -0.6373448967933655,
    -0.6668903827667236,
    -0.6956121921539307,
    -0.7221284508705139,
    -0.7442778944969177,
    -0.7603025436401367,
    -0.7702796459197998,
    -0.776165783405304,
    -0.7800728678703308,
    -0.7827072143554688,
    -0.7838994264602661,
    -0.7844712138175964,
    -0.7868678569793701,
    -0.7937839031219482,
    -0.8067249655723572,
    -0.8262118697166443,
    -0.8527114987373352,
    -0.8865681290626526,
    -0.92718106508255,
    -0.9731906056404114,
    -1.0239911079406738,
    -1.080629587173462,
    -1.1445175409317017,
    -1.2150743007659912,
    -1.2890511751174927,
    -1.3625744581222534,
    -1.4337596893310547,
    -1.5026825666427612,
    -1.5686581134796143,
    -1.628346562385559,
    -1.6776386499404907,
    -1.7153007984161377,
    -1.7437068223953247,
    -1.765954613685608,
    -1.784592866897583,
    -1.8061013221740723,
    -1.8472284078598022,
    -1.9349943399429321,
    -2.099210739135742,
    -2.3679637908935547,
    -2.7779700756073,
    -3.402205467224121,
    -4.39718770980835,
    -6.119454383850098,
    -9.607158660888672,
    -20.035425186157227,
    -20753036.0
  ],
  "sample_n_used": 179567
}